TA_Lib_binary.libs/libta_lib-3735de42.so.0.0.0
talib/stream.py
talib/test_pandas.py
talib/test_abstract.py
talib/__init__.py
talib/_ta_lib.cpython-38-x86_64-linux-gnu.so
talib/test_func.py
talib/deprecated.py
talib/test_stream.py
talib/test_data.py
talib/abstract.py
TA_Lib_binary-0.4.21.dist-info/WHEEL
TA_Lib_binary-0.4.21.dist-info/LICENSE
TA_Lib_binary-0.4.21.dist-info/RECORD
TA_Lib_binary-0.4.21.dist-info/AUTHORS
TA_Lib_binary-0.4.21.dist-info/METADATA
TA_Lib_binary-0.4.21.dist-info/top_level.txt
